seg2link_unet2d/__init__.py
seg2link_unet2d/preprocess.py
seg2link_unet2d/unet2.py
seg2link_unet2d-0.2.1.dist-info/METADATA
seg2link_unet2d-0.2.1.dist-info/WHEEL
seg2link_unet2d-0.2.1.dist-info/top_level.txt
seg2link_unet2d-0.2.1.dist-info/RECORD
